Workbook

Sheet Original Dataset
A1: store_id | B1: month | C1: region | D1: store_type | E1: marketing_spend | F1: footfall | G1: avg_discount_pct | H1: staff_count | I1: inventory_availability_pct | J1: competitor_distance_km | K1: holiday_flag | L1: customer_rating | M1: monthly_sales | N1: monthly_profit
A2: STR-1001 | B2: 2025-01-01 | C2: East | D2: Residential | E2: 70389.11 | F2: 8302 | G2: 0.042 | H2: 17 | I2: 75 | J2: 5.28 | K2: 1 | L2: 3.1 | M2: 658832.62 | N2: 84349.93
A3: STR-1001 | B3: 2025-02-01 | C3: East | D3: Residential | E3: 43827.89 | F3: 8487 | G3: 0.168 | H3: 23 | I3: 84.4 | J3: 4.31 | K3: 0 | L3: 2.8 | M3: 634436 | N3: 106130.54
A4: STR-1001 | B4: 2025-03-01 | C4: East | D4: Residential | E4: 59921.75 | F4: 9113 | G4: 0.133 | H4: 20 | I4: 88 | J4: 12 | K4: 0 | L4: 3.2 | M4: 678722.06 | N4: 101883.86
A5: STR-1001 | B5: 2025-04-01 | C5: East | D5: Residential | E5: 56856.63 | F5: 9431 | G5: 0.142 | H5: 23 | I5: 86.9 | J5: 4.97 | K5: 0 | L5: 3.4 | M5: 658920.3 | N5: 97910.37
A6: STR-1002 | B6: 2025-01-01 | C6: East | D6: High Street | E6: 48412.64 | F6: 9545 | G6: 0.231 | H6: 21 | I6: 97.6 | J6: 6.94 | K6: 1 | L6: 4.2 | M6: 741341.44 | N6: 119208.17
A7: STR-1002 | B7: 2025-02-01 | C7: East | D7: High Street | E7: 64811.21 | F7: 9792 | G7: 0.112 | H7: 20 | I7: 84.2 | J7: 2.88 | K7: 0 | L7: 4.2 | M7: 761835.34 | N7: 149602.23
A8: STR-1002 | B8: 2025-03-01 | C8: East | D8: High Street | E8: 46213.45 | F8: 10616 | G8: 0.122 | H8: 22 | I8: 85.2 | J8: 0.2 | K8: 1 | L8: 4.1 | M8: 806615.54 | N8: 131364.62
A9: STR-1002 | B9: 2025-04-01 | C9: East | D9: High Street | E9: 68148.52 | F9: 8567 | G9: 0.127 | H9: 23 | I9: 95.6 | J9: 0.8 | K9: 0 | L9: 3.9 | M9: 850164.26 | N9: 149262.75
A10: STR-1003 | B10: 2025-01-01 | C10: North | D10: Airport | E10: 71838.86 | F10: 10979 | G10: 0.215 | H10: 26 | I10: 88.6 | J10: 7.7 | K10: 1 | L10: 3.8 | M10: 930581.7 | N10: 136207.98
A11: STR-1003 | B11: 2025-02-01 | C11: North | D11: Airport | E11: 68133.44 | F11: 9459 | G11: 0.22 | H11: 21 | I11: 85 | J11: 1.91 | K11: 0 | L11: 4.2 | M11: 779010.94 | N11: 106328.09
A12: STR-1003 | B12: 2025-03-01 | C12: North | D12: Airport | E12: 34285.21 | F12: 9172 | G12: 0.213 | H12: 22 | I12: 88.3 | J12: 10.46 | K12: 1 | L12: 3.8 | M12: 723060.76 | N12: 123131.24
A13: STR-1003 | B13: 2025-04-01 | C13: North | D13: Airport | E13: 67979.88 | F13: 11230 | G13: 0.002 | H13: 28 | I13: 85.3 | J13: 7.16 | K13: 0 | L13: 3.8 | M13: 910791.94 | N13: 158891.28
... A34: STR-1009 | B34: 2025-01-01 | C34: North | D34: Residential | E34: 54597.83 | F34: 9429 | G34: 0.188 | H34: 21 | I34: 83.3 | J34: 11.71 | K34: 0 | L34: 4.2 | M34: 641865.03 | N34: 81342.58
A35: STR-1009 | B35: 2025-02-01 | C35: North | D35: Residential | E35: 73771.91 | F35: 11695 | G35: 0.07 | H35: 25 | I35: 84.7 | J35: 0.62 | K35: 0 | M35: 799477.76 | N35: 164974.41
A36: STR-1009 | B36: 2025-03-01 | C36: North | D36: Residential | E36: 74413.88 | F36: 9449 | G36: 0.039 | H36: 23 | I36: 92.1 | J36: 2.12 | K36: 0 | L36: 3.5 | M36: 798952.17 | N36: 161499.04
A37: STR-1009 | B37: 2025-04-01 | C37: North | D37: Residential | E37: 52483.77 | F37: 10453 | G37: 0.247 | H37: 25 | I37: 99 | J37: 6.31 | K37: 0 | L37: 3.6 | M37: 800979.78 | N37: 149242.27
A38: STR-1010 | B38: 2025-01-01 | C38: North | D38: Mall | E38: 75269.87 | F38: 8838 | G38: 0.092 | H38: 21 | I38: 83.1 | J38: 9.56 | K38: 1 | L38: 4.2 | M38: 820593.93 | N38: 115860.06
A39: STR-1010 | B39: 2025-02-01 | C39: North | D39: Mall | E39: 61245.41 | F39: 8156 | G39: 0.156 | H39: 19 | I39: 92.9 | J39: 9.05 | K39: 0 | L39: 3.8 | M39: 718330.53 | N39: 93247.9
A40: STR-1010 | B40: 2025-03-01 | C40: North | D40: Mall | E40: 93381.26 | F40: 7562 | G40: 0.198 | H40: 19 | I40: 82.9 | J40: 5.05 | K40: 0 | L40: 4 | M40: 736633.4 | N40: 115654.66
A41: STR-1010 | B41: 2025-04-01 | C41: North | D41: Mall | E41: 65012.19 | F41: 9598 | G41: 0.085 | H41: 24 | I41: 98.3 | J41: 0.89 | K41: 0 | L41: 3.8 | M41: 828623.85 | N41: 167320.52
A42: STR-1011 | B42: 2025-01-01 | C42: East | D42: Mall | E42: 40462.94 | F42: 3660 | G42: 0.218 | H42: 11 | I42: 95.2 | J42: 5.57 | K42: 0 | L42: 4.4 | M42: 592195.85 | N42: 92291.56
A43: STR-1011 | B43: 2025-02-01 | C43: East | D43: Mall | E43: 46123.88 | F43: 3227 | G43: 0.143 | H43: 10 | I43: 75.4 | J43: 1.06 | K43: 0 | L43: 4.4 | M43: 532644.46 | N43: 60681.32
A44: STR-1011 | B44: 2025-03-01 | C44: East | D44: Mall | E44: 68077.54 | F44: 3360 | G44: 0.128 | H44: 14 | I44: 88.2 | J44: 1.24 | K44: 1 | L44: 4 | M44: 657429.18 | N44: 88919.74
A45: STR-1011 | B45: 2025-04-01 | C45: East | D45: Mall | E45: 64882.14 | F45: 3642 | G45: 0.019 | H45: 13 | I45: 87.8 | J45: 4.52 | K45: 0 | L45: 4.2 | M45: 605178 | N45: 106958.74
A46: STR-1012 | B46: 2025-01-01 | C46: West | D46: Residential | E46: 138855.51 | F46: 5145 | G46: 0.06 | H46: 17 | I46: 88.2 | J46: 9.58 | K46: 0 | L46: 3.2 | M46: 595467.6 | N46: 104276.46
A47: STR-1012 | B47: 2025-02-01 | C47: West | D47: Residential | E47: 63630.21 | F47: 4460 | G47: 0.235 | H47: 14 | I47: 98.6 | J47: 5.52 | K47: 0 | L47: 3.5 | M47: 599603.4 | N47: 112685.12
... A72: STR-1018 | B72: 2025-03-01 | C72: East | D72: High Street | E72: 60571.82 | F72: 3193 | G72: 0.197 | H72: 7 | I72: 99 | J72: 1.43 | K72: 0 | L72: 3.2 | M72: 605023.87 | N72: 98545.81
A73: STR-1018 | B73: 2025-04-01 | C73: East | D73: High Street | E73: 55081.16 | F73: 5485 | G73: 0.036 | H73: 12 | I73: 88 | K73: 0 | L73: 3.5 | M73: 674774.09 | N73: 141917.59
A74: STR-1019 | B74: 2025-01-01 | C74: East | D74: Residential | E74: 46201.46 | F74: 5918 | G74: 0.277 | H74: 13 | I74: 78.8 | J74: 4.91 | K74: 0 | L74: 4.5 | M74: 616069.41 | N74: 54453.99
A75: STR-1019 | B75: 2025-02-01 | C75: East | D75: Residential | E75: 53762.92 | F75: 6821 | G75: 0.066 | H75: 19 | I75: 94.6 | J75: 7.03 | K75: 0 | L75: 4.4 | M75: 630829.94 | N75: 117090.02
A76: STR-1019 | B76: 2025-03-01 | C76: East | D76: Residential | E76: 70144.78 | F76: 6806 | G76: 0.178 | H76: 20 | I76: 93.1 | J76: 0.28 | K76: 1 | L76: 4.3 | M76: 788087.68 | N76: 116803.42
A77: STR-1019 | B77: 2025-04-01 | C77: East | D77: Residential | E77: 58749.63 | F77: 8252 | G77: 0.203 | H77: 20 | I77: 85.2 | J77: 3.61 | K77: 0 | L77: 4.5 | M77: 680840.36 | N77: 68007.68
A78: STR-1020 | B78: 2025-01-01 | C78: South | D78: High Street | E78: 56973.18 | F78: 6662 | G78: 0.1 | H78: 15 | I78: 77.7 | J78: 7.52 | K78: 1 | L78: 3.2 | M78: 643657.47 | N78: 87022.45
A79: STR-1020 | B79: 2025-02-01 | C79: South | D79: High Street | E79: 54872.82 | F79: 5962 | G79: 0.064 | H79: 12 | I79: 85.4 | J79: 2.58 | K79: 0 | L79: 2.9 | M79: 691112.6 | N79: 109212.83
A80: STR-1020 | B80: 2025-03-01 | C80: South | D80: High Street | E80: 80562.81 | F80: 7470 | G80: 0.172 | H80: 16 | I80: 83.5 | J80: 2.29 | K80: 0 | L80: 3.3 | M80: 776922.17 | N80: 150701.93
A81: STR-1020 | B81: 2025-04-01 | C81: South | D81: High Street | E81: 77999.9 | F81: 5974 | G81: 0.252 | H81: 14 | I81: 81.3 | J81: 2.39 | K81: 0 | L81: 3.2 | M81: 636561.34 | N81: 93861.06
A82: STR-1021 | B82: 2025-01-01 | C82: West | D82: Mall | E82: 60881.01 | F82: 5410 | G82: 0.179 | H82: 15 | I82: 83.9 | J82: 5.24 | K82: 0 | L82: 4.6 | M82: 621369.58 | N82: 85493.64
A83: STR-1021 | B83: 2025-02-01 | C83: West | D83: Mall | E83: 60628.38 | F83: 4451 | G83: 0.095 | H83: 10 | I83: 89.6 | J83: 3.17 | K83: 0 | L83: 4.6 | M83: 682208.01 | N83: 110318.84
A84: STR-1021 | B84: 2025-03-01 | C84: West | D84: Mall | E84: 72731.14 | F84: 4644 | G84: 0.084 | H84: 15 | I84: 87.1 | J84: 2.66 | K84: 0 | L84: 4.6 | M84: 727241.86 | N84: 155810.3
A85: STR-1021 | B85: 2025-04-01 | C85: West | D85: Mall | E85: 36475.71 | F85: 3559 | G85: 0.03 | H85: 8 | I85: 83.6 | J85: 1.41 | K85: 0 | L85: 4.2 | M85: 569100.78 | N85: 104808.78
A86: STR-1022 | B86: 2025-01-01 | C86: West | D86: High Street | E86: 55388.11 | F86: 3091 | G86: 0.108 | H86: 7 | I86: 85.4 | J86: 7.34 | K86: 0 | L86: 4.9 | M86: 574436.29 | N86: 80271.99
A87: STR-1022 | B87: 2025-02-01 | C87: West | D87: High Street | E87: 88443.77 | F87: 4004 | G87: 0.206 | H87: 11 | I87: 91.9 | J87: 5.95 | K87: 0 | M87: 611766.72 | N87: 88275.61
A88: STR-1022 | B88: 2025-03-01 | C88: West | D88: High Street | E88: 78231.91 | F88: 3788 | G88: 0.059 | H88: 11 | I88: 88.5 | J88: 15.51 | K88: 0 | L88: 4.3 | M88: 614596.32 | N88: 131199.41
A89: STR-1022 | B89: 2025-04-01 | C89: West | D89: High Street | E89: 18996.32 | F89: 1260 | G89: 0.145 | H89: 9 | I89: 86.4 | J89: 4.31 | K89: 0 | L89: 4.6 | M89: 450711.92 | N89: 90043.76
A90: STR-1023 | B90: 2025-01-01 | C90: South | D90: Mall | E90: 50517.94 | F90: 7024 | G90: 0.029 | H90: 18 | I90: 79.2 | J90: 6.61 | K90: 1 | L90: 4.1 | M90: 711213.46 | N90: 105863.26
A91: STR-1023 | B91: 2025-02-01 | C91: South | D91: Mall | E91: 141540.29 | F91: 5400 | G91: 0.013 | H91: 12 | I91: 87 | J91: 4.26 | K91: 0 | L91: 4.5 | M91: 627171.9 | N91: 105772.75
A92: STR-1023 | B92: 2025-03-01 | C92: South | D92: Mall | E92: 82116.19 | F92: 5988 | G92: 0.04 | H92: 17 | I92: 91.8 | J92: 5.75 | K92: 0 | L92: 4.7 | M92: 739852.58 | N92: 129386.43
A93: STR-1023 | B93: 2025-04-01 | C93: South | D93: Mall | E93: 31207.51 | F93: 3701 | G93: 0.043 | H93: 11 | I93: 84.7 | J93: 0.33 | K93: 0 | L93: 4.3 | M93: 586307.22 | N93: 73927.85
A94: STR-1024 | B94: 2025-01-01 | C94: West | D94: Residential | E94: 38966.59 | F94: 4509 | G94: 0.194 | H94: 14 | I94: 91.1 | J94: 2.92 | K94: 0 | L94: 4.6 | M94: 585937.48 | N94: 82624.2
A95: STR-1024 | B95: 2025-02-01 | C95: West | D95: Residential | E95: 67439.3 | F95: 6477 | G95: 0 | H95: 16 | I95: 90.9 | J95: 1.64 | K95: 0 | L95: 4.5 | M95: 753473.55 | N95: 151527.22
A96: STR-1024 | B96: 2025-03-01 | C96: West | D96: Residential | E96: 86421.88 | F96: 7970 | G96: 0.073 | H96: 17 | I96: 91.3 | J96: 0.8 | K96: 0 | L96: 5 | M96: 838250.32 | N96: 122939.34
A97: STR-1024 | B97: 2025-04-01 | C97: West | D97: Residential | E97: 9534.65 | F97: 6057 | G97: 0.074 | H97: 15 | I97: 94.1 | J97: 5.79 | K97: 0 | L97: 4.5 | M97: 607898.12 | N97: 135404.85
A98: STR-1025 | B98: 2025-01-01 | C98: West | D98: Mall | E98: 61132.07 | F98: 6394 | G98: 0.163 | H98: 19 | I98: 91 | J98: 19.6 | K98: 0 | L98: 4.4 | M98: 691113.62 | N98: 135145.44
A99: STR-1025 | B99: 2025-02-01 | C99: West | D99: Mall | E99: 78839.39 | F99: 5150 | G99: 0.171 | H99: 13 | I99: 85.8 | J99: 7.57 | K99: 0 | L99: 4.3 | M99: 735509.4 | N99: 83895.96
A100: STR-1025 | B100: 2025-03-01 | C100: West | D100: Mall | E100: 38752.8 | F100: 4712 | G100: 0.075 | H100: 15 | I100: 89.7 | K100: 0 | L100: 4.3 | M100: 605775.33 | N100: 107194.6
A101: STR-1025 | B101: 2025-04-01 | C101: West | D101: Mall | E101: 55101.1 | F101: 5281 | G101: 0.189 | H101: 11 | I101: 91 | J101: 2.7 | K101: 0 | L101: 4.4 | M101: 675177.68 | N101: 105628.68
A102: STR-1026 | B102: 2025-01-01 | C102: East | D102: Mall | E102: 53084.76 | F102: 3642 | G102: 0.15 | H102: 12 | I102: 91.4 | J102: 0.2 | K102: 0 | L102: 4.4 | M102: 635181.35 | N102: 83341.25
A103: STR-1026 | B103: 2025-02-01 | C103: East | D103: Mall | E103: 63101.59 | F103: 4373 | G103: 0.173 | H103: 14 | I103: 90.4 | J103: 7.87 | K103: 0 | L103: 4.7 | M103: 586626.94 | N103: 86498.55
A104: STR-1026 | B104: 2025-03-01 | C104: East | D104: Mall | E104: 90084.4 | F104: 6832 | G104: 0.185 | H104: 14 | I104: 80.5 | J104: 0.77 | K104: 1 | L104: 4.4 | M104: 740102.64 | N104: 114299.07
A105: STR-1026 | B105: 2025-04-01 | C105: East | D105: Mall | E105: 32266.64 | F105: 2414 | G105: 0.08 | H105: 7 | I105: 92.1 | J105: 1.48 | K105: 0 | L105: 5 | M105: 625514.04 | N105: 120685.08
A106: STR-1027 | B106: 2025-01-01 | C106: West | D106: High Street | E106: 57919.07 | F106: 7374 | G106: 0.103 | H106: 21 | I106: 82.3 | J106: 2.87 | K106: 0 | L106: 2.9 | M106: 727227.2 | N106: 121292.01
A107: STR-1027 | B107: 2025-02-01 | C107: West | D107: High Street | E107: 74679.35 | F107: 8739 | G107: 0.056 | H107: 21 | I107: 91.8 | J107: 2.83 | K107: 0 | L107: 3 | M107: 783797.89 | N107: 157620.7
A108: STR-1027 | B108: 2025-03-01 | C108: West | D108: High Street | E108: 64294.23 | F108: 6992 | G108: 0.133 | H108: 14 | I108: 94.1 | J108: 0.25 | K108: 0 | L108: 3 | M108: 795153.84 | N108: 143194.21
A109: STR-1027 | B109: 2025-04-01 | C109: West | D109: High Street | E109: 31042.03 | F109: 7107 | G109: 0.051 | H109: 15 | I109: 87 | J109: 13.33 | K109: 0 | L109: 3.2 | M109: 665594.94 | N109: 127597.34
A110: STR-1028 | B110: 2025-01-01 | C110: East | D110: Mall | E110: 75265.02 | F110: 6975 | G110: 0.157 | H110: 20 | I110: 73.8 | J110: 6.35 | K110: 1 | L110: 3.8 | M110: 709478.39 | N110: 71294.27
A111: STR-1028 | B111: 2025-02-01 | C111: East | D111: Mall | E111: 69411.7 | F111: 5493 | G111: 0.292 | H111: 13 | I111: 86.5 | J111: 6.69 | K111: 0 | L111: 3.8 | M111: 664162.49 | N111: 98291.06
A112: STR-1028 | B112: 2025-03-01 | C112: East | D112: Mall | E112: 51056.15 | F112: 5686 | G112: 0.089 | H112: 13 | I112: 89.9 | J112: 1.28 | K112: 0 | L112: 4.2 | M112: 633494.21 | N112: 105739.47
... A134: STR-1034 | B134: 2025-01-01 | C134: North | D134: High Street | E134: 70276.28 | F134: 3043 | G134: 0.079 | H134: 9 | I134: 87.9 | J134: 3.77 | K134: 0 | L134: 4.4 | M134: 527300.13 | N134: 84197.87
A135: STR-1034 | B135: 2025-02-01 | C135: North | D135: High Street | E135: 22071.64 | F135: 1814 | G135: 0.196 | H135: 8 | I135: 81.1 | J135: 0.78 | K135: 0 | M135: 400831.65 | N135: 70979.31
A136: STR-1034 | B136: 2025-03-01 | C136: North | D136: High Street | E136: 52285.45 | F136: 3618 | G136: 0.086 | H136: 11 | I136: 95.6 | J136: 5.17 | K136: 1 | L136: 4.4 | M136: 593247.25 | N136: 81240.29
A137: STR-1034 | B137: 2025-04-01 | C137: North | D137: High Street | E137: 70366.76 | F137: 1963 | G137: 0.182 | H137: 8 | I137: 89.8 | J137: 3.2 | K137: 0 | L137: 4.6 | M137: 529075.95 | N137: 95978.83
A138: STR-1035 | B138: 2025-01-01 | C138: South | D138: Residential | E138: 71320.66 | F138: 7888 | G138: 0.048 | H138: 20 | I138: 78.1 | J138: 3.4 | K138: 0 | M138: 633638.03 | N138: 99402.01
A139: STR-1035 | B139: 2025-02-01 | C139: South | D139: Residential | E139: 75109.67 | F139: 6244 | G139: 0.079 | H139: 15 | I139: 96.3 | J139: 7.38 | K139: 0 | L139: 3.7 | M139: 743348.84 | N139: 104186.09
A140: STR-1035 | B140: 2025-03-01 | C140: South | D140: Residential | E140: 69779 | F140: 6544 | G140: 0.152 | H140: 18 | I140: 90.2 | J140: 0.85 | K140: 1 | L140: 3.3 | M140: 758827.64 | N140: 161439.48
A141: STR-1035 | B141: 2025-04-01 | C141: South | D141: Residential | E141: 44211.95 | F141: 5465 | G141: 0.187 | H141: 12 | I141: 90 | J141: 2.89 | K141: 0 | L141: 3.6 | M141: 646559.71 | N141: 97981.75
A142: STR-1036 | B142: 2025-01-01 | C142: West | D142: High Street | E142: 51430.31 | F142: 6427 | G142: 0.234 | H142: 14 | I142: 88.8 | J142: 0.77 | K142: 0 | L142: 4.1 | M142: 715890.53 | N142: 109032.15
A143: STR-1036 | B143: 2025-02-01 | C143: West | D143: High Street | E143: 45706.49 | F143: 6704 | G143: 0.038 | H143: 15 | I143: 94.2 | J143: 2.92 | K143: 0 | L143: 4.2 | M143: 715097.57 | N143: 151875.86
A144: STR-1036 | B144: 2025-03-01 | C144: West | D144: High Street | E144: 44034.6 | F144: 5645 | G144: 0.069 | H144: 18 | I144: 88.5 | J144: 3.07 | K144: 0 | L144: 3.8 | M144: 682639.28 | N144: 77557.53
A145: STR-1036 | B145: 2025-04-01 | C145: West | D145: High Street | E145: 50198.12 | F145: 6089 | G145: 0.182 | H145: 19 | I145: 94 | J145: 9.7 | K145: 0 | L145: 3.9 | M145: 695098.51 | N145: 108192.75
A146: STR-1037 | B146: 2025-01-01 | C146: North | D146: Residential | E146: 70488.2 | F146: 4312 | G146: 0.169 | H146: 12 | I146: 90.2 | J146: 3.71 | K146: 0 | L146: 3.2 | M146: 577732.57 | N146: 93804.27
A147: STR-1037 | B147: 2025-02-01 | C147: North | D147: Residential | E147: 50909.27 | F147: 3152 | G147: 0.06 | H147: 13 | I147: 93.7 | J147: 10.79 | K147: 0 | L147: 3.5 | M147: 537058.33 | N147: 93555.71
A148: STR-1037 | B148: 2025-03-01 | C148: North | D148: Residential | E148: 53351.7 | F148: 4259 | G148: 0.156 | H148: 15 | I148: 93.7 | J148: 6.03 | K148: 0 | L148: 3.4 | M148: 601568.87 | N148: 91634.82
A149: STR-1037 | B149: 2025-04-01 | C149: North | D149: Residential | E149: 60322.4 | F149: 3350 | G149: 0.108 | H149: 12 | I149: 89.4 | J149: 4.92 | K149: 0 | L149: 3.4 | M149: 570964.84 | N149: 81331.07
A150: STR-1038 | B150: 2025-01-01 | C150: South | D150: Mall | E150: 51575.68 | F150: 5329 | G150: 0.047 | H150: 17 | I150: 88.1 | J150: 19.78 | K150: 0 | L150: 3.8 | M150: 614024.91 | N150: 84828.93
... A163: STR-1041 | B163: 2025-02-01 | C163: South | D163: High Street | E163: 48438.85 | F163: 6992 | G163: 0.034 | H163: 20 | I163: 91 | J163: 4.36 | K163: 0 | L163: 4.2 | M163: 778298.88 | N163: 130076.72
A164: STR-1041 | B164: 2025-03-01 | C164: South | D164: High Street | E164: 57143.3 | F164: 8038 | G164: 0.193 | H164: 17 | I164: 72.6 | K164: 0 | L164: 4.2 | M164: 677096.71 | N164: 97174.11
A165: STR-1041 | B165: 2025-04-01 | C165: South | D165: High Street | E165: 66870.62 | F165: 6055 | G165: 0.075 | H165: 19 | I165: 93.8 | J165: 0.54 | K165: 0 | L165: 4.3 | M165: 692008.64 | N165: 116337.87
A166: STR-1042 | B166: 2025-01-01 | C166: North | D166: Mall | E166: 72150.53 | F166: 9323 | G166: 0.157 | H166: 22 | I166: 82.9 | J166: 11.37 | K166: 1 | L166: 4.3 | M166: 825797.91 | N166: 130945.24
A167: STR-1042 | B167: 2025-02-01 | C167: North | D167: Mall | E167: 35303.3 | F167: 8789 | G167: 0.123 | H167: 22 | I167: 86.1 | J167: 9.43 | K167: 0 | L167: 4.2 | M167: 706285.52 | N167: 138014.72
A168: STR-1042 | B168: 2025-03-01 | C168: North | D168: Mall | E168: 30301.86 | F168: 6939 | G168: 0.09 | H168: 16 | I168: 90.3 | J168: 3.49 | K168: 0 | L168: 4 | M168: 665534.7 | N168: 113167.73
A169: STR-1042 | B169: 2025-04-01 | C169: North | D169: Mall | E169: 78432.14 | F169: 9440 | G169: 0.126 | H169: 23 | I169: 89.2 | J169: 7.86 | K169: 0 | L169: 4.1 | M169: 820729.29 | N169: 159325.47
A170: STR-1043 | B170: 2025-01-01 | C170: East | D170: Residential | E170: 62059.18 | F170: 9374 | G170: 0.136 | H170: 25 | I170: 87.1 | J170: 12.55 | K170: 0 | L170: 4.9 | M170: 739831.73 | N170: 119490.21
A171: STR-1043 | B171: 2025-02-01 | C171: East | D171: Residential | E171: 32834.48 | F171: 7576 | G171: 0.099 | H171: 15 | I171: 84.1 | J171: 3.48 | K171: 0 | L171: 5 | M171: 593637.14 | N171: 106648.14
A172: STR-1043 | B172: 2025-03-01 | C172: East | D172: Residential | E172: 50825.08 | F172: 8949 | G172: 0.157 | H172: 21 | I172: 84.7 | J172: 7.73 | K172: 0 | L172: 4.9 | M172: 769702.76 | N172: 158697
A173: STR-1043 | B173: 2025-04-01 | C173: East | D173: Residential | E173: 36606.51 | F173: 7671 | G173: 0.118 | H173: 18 | I173: 89.8 | J173: 0.25 | K173: 0 | L173: 4.4 | M173: 679731.57 | N173: 121546.42
A174: STR-1044 | B174: 2025-01-01 | C174: East | D174: Residential | E174: 65237.79 | F174: 8741 | G174: 0.157 | H174: 20 | I174: 94.4 | J174: 6.43 | K174: 0 | L174: 3.3 | M174: 780344.18 | N174: 118239.09
A175: STR-1044 | B175: 2025-02-01 | C175: East | D175: Residential | E175: 43645.98 | F175: 9480 | G175: 0.109 | H175: 22 | I175: 89 | J175: 2.11 | K175: 0 | L175: 3.1 | M175: 721364.11 | N175: 147272.81
A176: STR-1044 | B176: 2025-03-01 | C176: East | D176: Residential | E176: 68040.15 | F176: 9826 | G176: 0.125 | H176: 20 | I176: 83.9 | J176: 9.12 | K176: 0 | L176: 3.6 | M176: 758138.29 | N176: 132975.26
... A196: STR-1049 | B196: 2025-03-01 | C196: West | D196: Residential | E196: 40220.18 | F196: 3783 | G196: 0.089 | H196: 14 | I196: 86.6 | J196: 3.63 | K196: 0 | L196: 3.7 | M196: 559422.02 | N196: 73528.74
...

Sheet Data Dictionary
A1: Column | B1: Description
A2: store_id | B2: Unique store identifier.
A3: month | B3: Reporting month.
A4: region | B4: Business region.
A5: store_type | B5: Mall, High Street, Residential, or Airport.
A6: marketing_spend | B6: Monthly marketing spend for the store.
A7: footfall | B7: Monthly visitor count.
A8: avg_discount_pct | B8: Average discount percentage for the month.
A9: staff_count | B9: Number of store staff.
A10: inventory_availability_pct | B10: Average product availability percentage.
A11: competitor_distance_km | B11: Distance to nearest competitor.
A12: holiday_flag | B12: 1 if the month/store period had a meaningful holiday effect; otherwise 0.
... A15: monthly_profit | B15: Optional secondary business metric.

Sheet Cleaned Prepared Data
A1: record_id | B1: store_id | C1: month | D1: region | E1: store_type | F1: marketing_spend | G1: footfall | H1: avg_discount_pct | I1: staff_count | J1: inventory_availability_pct | K1: competitor_distance_km | L1: holiday_flag | M1: customer_rating | N1: monthly_sales | O1: monthly_profit | P1: customer_rating_missing_flag | Q1: competitor_distance_missing_flag | R1: cleaning_note
A2: 1 | B2: STR-1001 | C2: 2025-01-01 | D2: East | E2: Residential | F2: 70389.11 | G2: 8302 | H2: 0.042 | I2: 17 | J2: 75 | K2: 5.28 | L2: 1 | M2: 3.1 | N2: 658832.62 | O2: 84349.93 | P2: 0 | Q2: 0 | R2: Clean
A3: 2 | B3: STR-1001 | C3: 2025-02-01 | D3: East | E3: Residential | F3: 43827.89 | G3: 8487 | H3: 0.168 | I3: 23 | J3: 84.4 | K3: 4.31 | L3: 0 | M3: 2.8 | N3: 634436 | O3: 106130.54 | P3: 0 | Q3: 0 | R3: Clean
A4: 3 | B4: STR-1001 | C4: 2025-03-01 | D4: East | E4: Residential | F4: 59921.75 | G4: 9113 | H4: 0.133 | I4: 20 | J4: 88 | K4: 12 | L4: 0 | M4: 3.2 | N4: 678722.06 | O4: 101883.86 | P4: 0 | Q4: 0 | R4: Clean
A5: 4 | B5: STR-1001 | C5: 2025-04-01 | D5: East | E5: Residential | F5: 56856.63 | G5: 9431 | H5: 0.142 | I5: 23 | J5: 86.9 | K5: 4.97 | L5: 0 | M5: 3.4 | N5: 658920.3 | O5: 97910.37 | P5: 0 | Q5: 0 | R5: Clean
A6: 5 | B6: STR-1002 | C6: 2025-01-01 | D6: East | E6: High Street | F6: 48412.64 | G6: 9545 | H6: 0.231 | I6: 21 | J6: 97.6 | K6: 6.94 | L6: 1 | M6: 4.2 | N6: 741341.44 | O6: 119208.17 | P6: 0 | Q6: 0 | R6: Clean
A7: 6 | B7: STR-1002 | C7: 2025-02-01 | D7: East | E7: High Street | F7: 64811.21 | G7: 9792 | H7: 0.112 | I7: 20 | J7: 84.2 | K7: 2.88 | L7: 0 | M7: 4.2 | N7: 761835.34 | O7: 149602.23 | P7: 0 | Q7: 0 | R7: Clean
A8: 7 | B8: STR-1002 | C8: 2025-03-01 | D8: East | E8: High Street | F8: 46213.45 | G8: 10616 | H8: 0.122 | I8: 22 | J8: 85.2 | K8: 0.2 | L8: 1 | M8: 4.1 | N8: 806615.54 | O8: 131364.62 | P8: 0 | Q8: 0 | R8: Clean
A9: 8 | B9: STR-1002 | C9: 2025-04-01 | D9: East | E9: High Street | F9: 68148.52 | G9: 8567 | H9: 0.127 | I9: 23 | J9: 95.6 | K9: 0.8 | L9: 0 | M9: 3.9 | N9: 850164.26 | O9: 149262.75 | P9: 0 | Q9: 0 | R9: Clean
A10: 9 | B10: STR-1003 | C10: 2025-01-01 | D10: North | E10: Airport | F10: 71838.86 | G10: 10979 | H10: 0.215 | I10: 26 | J10: 88.6 | K10: 7.7 | L10: 1 | M10: 3.8 | N10: 930581.7 | O10: 136207.98 | P10: 0 | Q10: 0 | R10: Clean
A11: 10 | B11: STR-1003 | C11: 2025-02-01 | D11: North | E11: Airport | F11: 68133.44 | G11: 9459 | H11: 0.22 | I11: 21 | J11: 85 | K11: 1.91 | L11: 0 | M11: 4.2 | N11: 779010.94 | O11: 106328.09 | P11: 0 | Q11: 0 | R11: Clean
A12: 11 | B12: STR-1003 | C12: 2025-03-01 | D12: North | E12: Airport | F12: 34285.21 | G12: 9172 | H12: 0.213 | I12: 22 | J12: 88.3 | K12: 10.46 | L12: 1 | M12: 3.8 | N12: 723060.76 | O12: 123131.24 | P12: 0 | Q12: 0 | R12: Clean
A13: 12 | B13: STR-1003 | C13: 2025-04-01 | D13: North | E13: Airport | F13: 67979.88 | G13: 11230 | H13: 0.002 | I13: 28 | J13: 85.3 | K13: 7.16 | L13: 0 | M13: 3.8 | N13: 910791.94 | O13: 158891.28 | P13: 0 | Q13: 0 | R13: Clean
... A321: 320 | B321: STR-1080 | C321: 2025-04-01 | D321: East | E321: Residential | F321: 40553.11 | G321: 5317 | H321: 0.165 | I321: 17 | J321: 84.3 | K321: 11.82 | L321: 0 | M321: 4.1 | N321: 559660.84 | O321: 71443.61 | P321: 0 | Q321: 0 | R321: Clean

Sheet Dummy Variables
A1: record_id | B1: store_id | C1: region | D1: store_type | E1: store_type_High_Street | F1: store_type_Mall | G1: store_type_Residential | H1: region_North | I1: region_South | J1: region_West | K1: reference_categories
A2: 1 | B2: STR-1001 | C2: East | D2: Residential | E2: =IF(D2="High Street",1,0) -> 0 | F2: =IF(D2="Mall",1,0) -> 0 | G2: =IF(D2="Residential",1,0) -> 1 | H2: =IF(C2="North",1,0) -> 0 | I2: =IF(C2="South",1,0) -> 0 | J2: =IF(C2="West",1,0) -> 0 | K2: store_type reference = Airport; region reference = East
A3: 2 | B3: STR-1001 | C3: East | D3: Residential | E3: =IF(D3="High Street",1,0) -> 0 | F3: =IF(D3="Mall",1,0) -> 0 | G3: =IF(D3="Residential",1,0) -> 1 | H3: =IF(C3="North",1,0) -> 0 | I3: =IF(C3="South",1,0) -> 0 | J3: =IF(C3="West",1,0) -> 0 | K3: store_type reference = Airport; region reference = East
A4: 3 | B4: STR-1001 | C4: East | D4: Residential | E4: =IF(D4="High Street",1,0) -> 0 | F4: =IF(D4="Mall",1,0) -> 0 | G4: =IF(D4="Residential",1,0) -> 1 | H4: =IF(C4="North",1,0) -> 0 | I4: =IF(C4="South",1,0) -> 0 | J4: =IF(C4="West",1,0) -> 0 | K4: store_type reference = Airport; region reference = East
A5: 4 | B5: STR-1001 | C5: East | D5: Residential | E5: =IF(D5="High Street",1,0) -> 0 | F5: =IF(D5="Mall",1,0) -> 0 | G5: =IF(D5="Residential",1,0) -> 1 | H5: =IF(C5="North",1,0) -> 0 | I5: =IF(C5="South",1,0) -> 0 | J5: =IF(C5="West",1,0) -> 0 | K5: store_type reference = Airport; region reference = East
A6: 5 | B6: STR-1002 | C6: East | D6: High Street | E6: =IF(D6="High Street",1,0) -> 1 | F6: =IF(D6="Mall",1,0) -> 0 | G6: =IF(D6="Residential",1,0) -> 0 | H6: =IF(C6="North",1,0) -> 0 | I6: =IF(C6="South",1,0) -> 0 | J6: =IF(C6="West",1,0) -> 0 | K6: store_type reference = Airport; region reference = East
A7: 6 | B7: STR-1002 | C7: East | D7: High Street | E7: =IF(D7="High Street",1,0) -> 1 | F7: =IF(D7="Mall",1,0) -> 0 | G7: =IF(D7="Residential",1,0) -> 0 | H7: =IF(C7="North",1,0) -> 0 | I7: =IF(C7="South",1,0) -> 0 | J7: =IF(C7="West",1,0) -> 0 | K7: store_type reference = Airport; region reference = East
A8: 7 | B8: STR-1002 | C8: East | D8: High Street | E8: =IF(D8="High Street",1,0) -> 1 | F8: =IF(D8="Mall",1,0) -> 0 | G8: =IF(D8="Residential",1,0) -> 0 | H8: =IF(C8="North",1,0) -> 0 | I8: =IF(C8="South",1,0) -> 0 | J8: =IF(C8="West",1,0) -> 0 | K8: store_type reference = Airport; region reference = East
A9: 8 | B9: STR-1002 | C9: East | D9: High Street | E9: =IF(D9="High Street",1,0) -> 1 | F9: =IF(D9="Mall",1,0) -> 0 | G9: =IF(D9="Residential",1,0) -> 0 | H9: =IF(C9="North",1,0) -> 0 | I9: =IF(C9="South",1,0) -> 0 | J9: =IF(C9="West",1,0) -> 0 | K9: store_type reference = Airport; region reference = East
A10: 9 | B10: STR-1003 | C10: North | D10: Airport | E10: =IF(D10="High Street",1,0) -> 0 | F10: =IF(D10="Mall",1,0) -> 0 | G10: =IF(D10="Residential",1,0) -> 0 | H10: =IF(C10="North",1,0) -> 1 | I10: =IF(C10="South",1,0) -> 0 | J10: =IF(C10="West",1,0) -> 0 | K10: store_type reference = Airport; region reference = East
A11: 10 | B11: STR-1003 | C11: North | D11: Airport | E11: =IF(D11="High Street",1,0) -> 0 | F11: =IF(D11="Mall",1,0) -> 0 | G11: =IF(D11="Residential",1,0) -> 0 | H11: =IF(C11="North",1,0) -> 1 | I11: =IF(C11="South",1,0) -> 0 | J11: =IF(C11="West",1,0) -> 0 | K11: store_type reference = Airport; region reference = East
A12: 11 | B12: STR-1003 | C12: North | D12: Airport | E12: =IF(D12="High Street",1,0) -> 0 | F12: =IF(D12="Mall",1,0) -> 0 | G12: =IF(D12="Residential",1,0) -> 0 | H12: =IF(C12="North",1,0) -> 1 | I12: =IF(C12="South",1,0) -> 0 | J12: =IF(C12="West",1,0) -> 0 | K12: store_type reference = Airport; region reference = East
A13: 12 | B13: STR-1003 | C13: North | D13: Airport | E13: =IF(D13="High Street",1,0) -> 0 | F13: =IF(D13="Mall",1,0) -> 0 | G13: =IF(D13="Residential",1,0) -> 0 | H13: =IF(C13="North",1,0) -> 1 | I13: =IF(C13="South",1,0) -> 0 | J13: =IF(C13="West",1,0) -> 0 | K13: store_type reference = Airport; region reference = East
... A321: 320 | B321: STR-1080 | C321: East | D321: Residential | E321: =IF(D321="High Street",1,0) -> 0 | F321: =IF(D321="Mall",1,0) -> 0 | G321: =IF(D321="Residential",1,0) -> 1 | H321: =IF(C321="North",1,0) -> 0 | I321: =IF(C321="South",1,0) -> 0 | J321: =IF(C321="West",1,0) -> 0 | K321: store_type reference = Airport; region reference = East

Sheet Simple Regression Outputs
A1: Simple Regression Outputs: monthly_sales as Dependent Variable
A3: Model name | B3: Dependent variable | C3: Independent variable | D3: Regression equation | E3: R-squared | F3: Coefficient | G3: P-value | H3: Business interpretation | I3: Useful?
A4: Simple: marketing_spend | B4: monthly_sales | C4: marketing_spend | D4: monthly_sales = 560,777.35 + (2.1296 × marketing_spend) | E4: 0.16724469 | F4: 2.1295753 | G4: 2.4868996e-14 | H4: Each additional currency unit of marketing spend is associated with about 2.13 more sales. | I4: Useful
A5: Simple: footfall | B5: monthly_sales | C5: footfall | D5: monthly_sales = 446,410.58 + (35.6780 × footfall) | E5: 0.73628534 | F5: 35.678031 | G5: 0 | H5: Each additional visitor is associated with about 35.68 more sales; strongest simple model. | I5: Useful
A6: Simple: avg_discount_pct | B6: monthly_sales | C6: avg_discount_pct | D6: monthly_sales = 697,835.63 + (-138,730.4547 × avg_discount_pct) | E6: 0.008290503 | F6: -138730.45 | G6: 0.10399305 | H6: Higher discounting has a weak negative relationship in the simple model; do not treat as a proven discount effect. | I6: Not useful alone
A7: Simple: inventory_availability_pct | B7: monthly_sales | C7: inventory_availability_pct | D7: monthly_sales = 484,814.26 + (2,217.8319 × inventory_availability_pct) | E7: 0.013115016 | F7: 2217.8319 | G7: 0.040625297 | H7: Each 1 percentage-point increase in availability is associated with about 2,218 more sales. | I7: Useful but low explanatory power
A8: Simple: customer_rating | B8: monthly_sales | C8: customer_rating | D8: monthly_sales = 701,366.86 + (-5,284.8663 × customer_rating) | E8: 0.00069845266 | F8: -5284.8663 | G8: 0.63764415 | H8: Customer rating is weak in the simple model, likely because other store factors explain more of the sales variation. | I8: Not useful alone
A9: Simple: staff_count | B9: monthly_sales | C9: staff_count | D9: monthly_sales = 400,551.47 + (16,984.0288 × staff_count) | E9: 0.65229045 | F9: 16984.029 | G9: 0 | H9: Each additional staff member is associated with about 16,984 more sales in the simple model. | I9: Useful
A10: Simple: competitor_distance_km | B10: monthly_sales | C10: competitor_distance_km | D10: monthly_sales = 692,482.82 + (-2,612.9596 × competitor_distance_km) | E10: 0.011443607 | F10: -2612.9596 | G10: 0.055924495 | H10: Stores farther from competitors tend to have slightly higher sales, but evidence is borderline in the simple model. | I10: Borderline
A11: Simple: holiday_flag | B11: monthly_sales | C11: holiday_flag | D11: monthly_sales = 671,411.86 + (53,625.3354 × holiday_flag) | E11: 0.038128574 | F11: 53625.335 | G11: 0.00044270737 | H11: Holiday periods are associated with about 53,625 higher sales in the simple model. | I11: Useful but low explanatory power
A15: Selected Simple Model Detail | B15: Value
A16: Model | B16: Simple: footfall
A17: Observations | B17: 320
A18: R-squared | B18: 0.73628534
A19: Adjusted R-squared | B19: 0.73545605
A20: RMSE | B20: 53373.736
A21: Coefficient table
A22: Term | B22: Coefficient | C22: Standard Error | D22: P-value
A23: Intercept | B23: 446410.58 | C23: 8407.7383 | D23: 0
A24: footfall | B24: 35.678031 | C24: 1.1973783 | D24: 0

Sheet Multiple Regression Outputs
A1: Multiple Regression Output: Final Selected Model
A3: Metric | B3: Value
A4: Dependent variable | B4: monthly_sales
A5: Observations | B5: 320
A6: R-squared | B6: 0.85698739
A7: Adjusted R-squared | B7: 0.85042287
A8: RMSE | B8: 40133.893
A9: Reference category - store_type | B9: Airport
A10: Reference category - region | B10: East
A13: Variable | B13: Coefficient | C13: Standard Error | D13: t-stat | E13: P-value | F13: Direction | G13: Business meaning
A14: Intercept | B14: 86319.145 | C14: 44919.542 | D14: 1.921639 | E14: 0.05558282 | F14: Positive | G14: Expected sales for Airport stores in East region when numeric predictors are zero; mainly a baseline.
A15: marketing_spend | B15: 1.2099285 | C15: 0.11693921 | D15: 10.346645 | E15: 0 | F15: Positive | G15: Higher marketing spend is associated with higher monthly sales, holding other variables constant.
A16: footfall | B16: 27.336195 | C16: 2.3063597 | D16: 11.852529 | E16: 0 | F16: Positive | G16: Higher visitor count is strongly associated with higher monthly sales.
A17: avg_discount_pct | B17: -41243.149 | C17: 33875.971 | D17: -1.217475 | E17: 0.22436463 | F17: Negative | G17: Weak/uncertain discount relationship after controls; do not over-interpret.
A18: staff_count | B18: 3508.3992 | C18: 1161.8068 | D18: 3.0197784 | E18: 0.0027434138 | F18: Positive | G18: More staff is associated with higher sales, but may also proxy for larger/busier stores.
A19: inventory_availability_pct | B19: 3062.2103 | C19: 426.10271 | D19: 7.1865544 | E19: 5.1341154e-12 | F19: Positive | G19: Better availability is associated with higher sales; stockouts likely constrain performance.
A20: competitor_distance_km | B20: -3438.1079 | C20: 540.28004 | D20: -6.3635664 | E20: 7.2150952e-10 | F20: Negative | G20: Stores farther from competitors have higher sales, suggesting competition pressure.
A21: holiday_flag | B21: 15157.287 | C21: 6127.8092 | D21: 2.4735247 | E21: 0.013923164 | F21: Positive | G21: Holiday months are associated with higher sales.
A22: customer_rating | B22: 12509.461 | C22: 4448.8856 | D22: 2.8118191 | E22: 0.0052453969 | F22: Positive | G22: Better customer rating is associated with higher sales after controls.
A23: store_type_High_Street | B23: -24475.836 | C23: 8614.8502 | D23: -2.8411215 | E23: 0.0047981654 | F23: Negative | G23: Difference versus Airport stores, holding other variables constant.
A24: store_type_Mall | B24: -11862.241 | C24: 8968.0125 | D24: -1.322728 | E24: 0.18691674 | F24: Negative | G24: Difference versus Airport stores, holding other variables constant.
A25: store_type_Residential | B25: -44695.095 | C25: 8748.7921 | D25: -5.1087161 | E25: 5.7286744e-07 | F25: Negative | G25: Difference versus Airport stores, holding other variables constant.
... A28: region_West | B28: 25291.419 | C28: 5898.7976 | D28: 4.287555 | E28: 2.4264745e-05 | F28: Positive | G28: Difference versus East region, holding other variables constant.

Sheet Prediction & Residuals
A1: record_id | B1: store_id | C1: month | D1: region | E1: store_type | F1: actual_monthly_sales | G1: marketing_spend | H1: footfall | I1: avg_discount_pct | J1: staff_count | K1: inventory_availability_pct | L1: competitor_distance_km | M1: holiday_flag | N1: customer_rating | O1: store_type_High_Street | P1: store_type_Mall | Q1: store_type_Residential | R1: region_North | S1: region_South | T1: region_West | U1: predicted_sales | V1: residual | X1: Largest Positive Residuals
A2: 1 | B2: STR-1001 | C2: 2025-01-01 | D2: East | E2: Residential | F2: 658832.62 | G2: 70389.11 | H2: 8302 | I2: 0.042 | J2: 17 | K2: 75 | L2: 5.28 | M2: 1 | N2: 3.1 | O2: 0 | P2: 0 | Q2: 1 | R2: 0 | S2: 0 | T2: 0 | U2: ='Multiple Regression Outputs'!$B$14+G2*'Multiple Regression Outputs'!$B$15+H2*'Multiple Regression Outputs'!$B$16+I2*'Multiple Regression Outputs'!$B$17+J2*'Multiple Regression Outputs'!$B$18+K2*'Multiple Regression Outputs'!$B$19+L2*'Multiple Regression Outputs'!$B$20+M2*'Multiple Regression Outputs'!$B$21+N2*'Multiple Regression Outputs'!$B$22+O2*'Multiple Regression Outputs'!$B$23+P2*'Multiple Regression Outputs'!$B$24+Q2*'Multiple Regression Outputs'!$B$25+R2*'Multiple Regression Outputs'!$B$26+S2*'Multiple Regression Outputs'!$B$27+T2*'Multiple Regression Outputs'!$B$28 -> 677094.68 | V2: =F2-U2 -> -18262.062 | X2: store_id | Y2: month | Z2: region | AA2: store_type | AB2: actual_sales | AC2: predicted_sales | AD2: residual
A3: 2 | B3: STR-1001 | C3: 2025-02-01 | D3: East | E3: Residential | F3: 634436 | G3: 43827.89 | H3: 8487 | I3: 0.168 | J3: 23 | K3: 84.4 | L3: 4.31 | M3: 0 | N3: 2.8 | O3: 0 | P3: 0 | Q3: 1 | R3: 0 | S3: 0 | T3: 0 | U3: ='Multiple Regression Outputs'!$B$14+G3*'Multiple Regression Outputs'!$B$15+H3*'Multiple Regression Outputs'!$B$16+I3*'Multiple Regression Outputs'!$B$17+J3*'Multiple Regression Outputs'!$B$18+K3*'Multiple Regression Outputs'!$B$19+L3*'Multiple Regression Outputs'!$B$20+M3*'Multiple Regression Outputs'!$B$21+N3*'Multiple Regression Outputs'!$B$22+O3*'Multiple Regression Outputs'!$B$23+P3*'Multiple Regression Outputs'!$B$24+Q3*'Multiple Regression Outputs'!$B$25+R3*'Multiple Regression Outputs'!$B$26+S3*'Multiple Regression Outputs'!$B$27+T3*'Multiple Regression Outputs'!$B$28 -> 679078.07 | V3: =F3-U3 -> -44642.075 | X3: STR-1058 | Y3: 2025-02-01 | Z3: East | AA3: High Street | AB3: 870937.4 | AC3: 759919.94 | AD3: 111017.46
A4: 3 | B4: STR-1001 | C4: 2025-03-01 | D4: East | E4: Residential | F4: 678722.06 | G4: 59921.75 | H4: 9113 | I4: 0.133 | J4: 20 | K4: 88 | L4: 12 | M4: 0 | N4: 3.2 | O4: 0 | P4: 0 | Q4: 1 | R4: 0 | S4: 0 | T4: 0 | U4: ='Multiple Regression Outputs'!$B$14+G4*'Multiple Regression Outputs'!$B$15+H4*'Multiple Regression Outputs'!$B$16+I4*'Multiple Regression Outputs'!$B$17+J4*'Multiple Regression Outputs'!$B$18+K4*'Multiple Regression Outputs'!$B$19+L4*'Multiple Regression Outputs'!$B$20+M4*'Multiple Regression Outputs'!$B$21+N4*'Multiple Regression Outputs'!$B$22+O4*'Multiple Regression Outputs'!$B$23+P4*'Multiple Regression Outputs'!$B$24+Q4*'Multiple Regression Outputs'!$B$25+R4*'Multiple Regression Outputs'!$B$26+S4*'Multiple Regression Outputs'!$B$27+T4*'Multiple Regression Outputs'!$B$28 -> 696169.96 | V4: =F4-U4 -> -17447.897 | X4: STR-1028 | Y4: 2025-04-01 | Z4: East | AA4: Mall | AB4: 713611.16 | AC4: 610531.95 | AD4: 103079.21
A5: 4 | B5: STR-1001 | C5: 2025-04-01 | D5: East | E5: Residential | F5: 658920.3 | G5: 56856.63 | H5: 9431 | I5: 0.142 | J5: 23 | K5: 86.9 | L5: 4.97 | M5: 0 | N5: 3.4 | O5: 0 | P5: 0 | Q5: 1 | R5: 0 | S5: 0 | T5: 0 | U5: ='Multiple Regression Outputs'!$B$14+G5*'Multiple Regression Outputs'!$B$15+H5*'Multiple Regression Outputs'!$B$16+I5*'Multiple Regression Outputs'!$B$17+J5*'Multiple Regression Outputs'!$B$18+K5*'Multiple Regression Outputs'!$B$19+L5*'Multiple Regression Outputs'!$B$20+M5*'Multiple Regression Outputs'!$B$21+N5*'Multiple Regression Outputs'!$B$22+O5*'Multiple Regression Outputs'!$B$23+P5*'Multiple Regression Outputs'!$B$24+Q5*'Multiple Regression Outputs'!$B$25+R5*'Multiple Regression Outputs'!$B$26+S5*'Multiple Regression Outputs'!$B$27+T5*'Multiple Regression Outputs'!$B$28 -> 734611.66 | V5: =F5-U5 -> -75691.359 | X5: STR-1073 | Y5: 2025-03-01 | Z5: East | AA5: Residential | AB5: 813316.71 | AC5: 721415.92 | AD5: 91900.79
A6: 5 | B6: STR-1002 | C6: 2025-01-01 | D6: East | E6: High Street | F6: 741341.44 | G6: 48412.64 | H6: 9545 | I6: 0.231 | J6: 21 | K6: 97.6 | L6: 6.94 | M6: 1 | N6: 4.2 | O6: 1 | P6: 0 | Q6: 0 | R6: 0 | S6: 0 | T6: 0 | U6: ='Multiple Regression Outputs'!$B$14+G6*'Multiple Regression Outputs'!$B$15+H6*'Multiple Regression Outputs'!$B$16+I6*'Multiple Regression Outputs'!$B$17+J6*'Multiple Regression Outputs'!$B$18+K6*'Multiple Regression Outputs'!$B$19+L6*'Multiple Regression Outputs'!$B$20+M6*'Multiple Regression Outputs'!$B$21+N6*'Multiple Regression Outputs'!$B$22+O6*'Multiple Regression Outputs'!$B$23+P6*'Multiple Regression Outputs'!$B$24+Q6*'Multiple Regression Outputs'!$B$25+R6*'Multiple Regression Outputs'!$B$26+S6*'Multiple Regression Outputs'!$B$27+T6*'Multiple Regression Outputs'!$B$28 -> 788200.62 | V6: =F6-U6 -> -46859.176 | X6: STR-1051 | Y6: 2025-02-01 | Z6: East | AA6: Airport | AB6: 787715.51 | AC6: 701381.34 | AD6: 86334.173
A7: 6 | B7: STR-1002 | C7: 2025-02-01 | D7: East | E7: High Street | F7: 761835.34 | G7: 64811.21 | H7: 9792 | I7: 0.112 | J7: 20 | K7: 84.2 | L7: 2.88 | M7: 0 | N7: 4.2 | O7: 1 | P7: 0 | Q7: 0 | R7: 0 | S7: 0 | T7: 0 | U7: ='Multiple Regression Outputs'!$B$14+G7*'Multiple Regression Outputs'!$B$15+H7*'Multiple Regression Outputs'!$B$16+I7*'Multiple Regression Outputs'!$B$17+J7*'Multiple Regression Outputs'!$B$18+K7*'Multiple Regression Outputs'!$B$19+L7*'Multiple Regression Outputs'!$B$20+M7*'Multiple Regression Outputs'!$B$21+N7*'Multiple Regression Outputs'!$B$22+O7*'Multiple Regression Outputs'!$B$23+P7*'Multiple Regression Outputs'!$B$24+Q7*'Multiple Regression Outputs'!$B$25+R7*'Multiple Regression Outputs'!$B$26+S7*'Multiple Regression Outputs'!$B$27+T7*'Multiple Regression Outputs'!$B$28 -> 773961.1 | V7: =F7-U7 -> -12125.762 | X7: STR-1026 | Y7: 2025-04-01 | Z7: East | AA7: Mall | AB7: 625514.04 | AC7: 540234.62 | AD7: 85279.419
A8: 7 | B8: STR-1002 | C8: 2025-03-01 | D8: East | E8: High Street | F8: 806615.54 | G8: 46213.45 | H8: 10616 | I8: 0.122 | J8: 22 | K8: 85.2 | L8: 0.2 | M8: 1 | N8: 4.1 | O8: 1 | P8: 0 | Q8: 0 | R8: 0 | S8: 0 | T8: 0 | U8: ='Multiple Regression Outputs'!$B$14+G8*'Multiple Regression Outputs'!$B$15+H8*'Multiple Regression Outputs'!$B$16+I8*'Multiple Regression Outputs'!$B$17+J8*'Multiple Regression Outputs'!$B$18+K8*'Multiple Regression Outputs'!$B$19+L8*'Multiple Regression Outputs'!$B$20+M8*'Multiple Regression Outputs'!$B$21+N8*'Multiple Regression Outputs'!$B$22+O8*'Multiple Regression Outputs'!$B$23+P8*'Multiple Regression Outputs'!$B$24+Q8*'Multiple Regression Outputs'!$B$25+R8*'Multiple Regression Outputs'!$B$26+S8*'Multiple Regression Outputs'!$B$27+T8*'Multiple Regression Outputs'!$B$28 -> 806771.21 | V8: =F8-U8 -> -155.67394
A9: 8 | B9: STR-1002 | C9: 2025-04-01 | D9: East | E9: High Street | F9: 850164.26 | G9: 68148.52 | H9: 8567 | I9: 0.127 | J9: 23 | K9: 95.6 | L9: 0.8 | M9: 0 | N9: 3.9 | O9: 1 | P9: 0 | Q9: 0 | R9: 0 | S9: 0 | T9: 0 | U9: ='Multiple Regression Outputs'!$B$14+G9*'Multiple Regression Outputs'!$B$15+H9*'Multiple Regression Outputs'!$B$16+I9*'Multiple Regression Outputs'!$B$17+J9*'Multiple Regression Outputs'!$B$18+K9*'Multiple Regression Outputs'!$B$19+L9*'Multiple Regression Outputs'!$B$20+M9*'Multiple Regression Outputs'!$B$21+N9*'Multiple Regression Outputs'!$B$22+O9*'Multiple Regression Outputs'!$B$23+P9*'Multiple Regression Outputs'!$B$24+Q9*'Multiple Regression Outputs'!$B$25+R9*'Multiple Regression Outputs'!$B$26+S9*'Multiple Regression Outputs'!$B$27+T9*'Multiple Regression Outputs'!$B$28 -> 792726.34 | V9: =F9-U9 -> 57437.917 | X9: Largest Negative Residuals
A10: 9 | B10: STR-1003 | C10: 2025-01-01 | D10: North | E10: Airport | F10: 930581.7 | G10: 71838.86 | H10: 10979 | I10: 0.215 | J10: 26 | K10: 88.6 | L10: 7.7 | M10: 1 | N10: 3.8 | O10: 0 | P10: 0 | Q10: 0 | R10: 1 | S10: 0 | T10: 0 | U10: ='Multiple Regression Outputs'!$B$14+G10*'Multiple Regression Outputs'!$B$15+H10*'Multiple Regression Outputs'!$B$16+I10*'Multiple Regression Outputs'!$B$17+J10*'Multiple Regression Outputs'!$B$18+K10*'Multiple Regression Outputs'!$B$19+L10*'Multiple Regression Outputs'!$B$20+M10*'Multiple Regression Outputs'!$B$21+N10*'Multiple Regression Outputs'!$B$22+O10*'Multiple Regression Outputs'!$B$23+P10*'Multiple Regression Outputs'!$B$24+Q10*'Multiple Regression Outputs'!$B$25+R10*'Multiple Regression Outputs'!$B$26+S10*'Multiple Regression Outputs'!$B$27+T10*'Multiple Regression Outputs'!$B$28 -> 873194.57 | V10: =F10-U10 -> 57387.133 | X10: store_id | Y10: month | Z10: region | AA10: store_type | AB10: actual_sales | AC10: predicted_sales | AD10: residual
A11: 10 | B11: STR-1003 | C11: 2025-02-01 | D11: North | E11: Airport | F11: 779010.94 | G11: 68133.44 | H11: 9459 | I11: 0.22 | J11: 21 | K11: 85 | L11: 1.91 | M11: 0 | N11: 4.2 | O11: 0 | P11: 0 | Q11: 0 | R11: 1 | S11: 0 | T11: 0 | U11: ='Multiple Regression Outputs'!$B$14+G11*'Multiple Regression Outputs'!$B$15+H11*'Multiple Regression Outputs'!$B$16+I11*'Multiple Regression Outputs'!$B$17+J11*'Multiple Regression Outputs'!$B$18+K11*'Multiple Regression Outputs'!$B$19+L11*'Multiple Regression Outputs'!$B$20+M11*'Multiple Regression Outputs'!$B$21+N11*'Multiple Regression Outputs'!$B$22+O11*'Multiple Regression Outputs'!$B$23+P11*'Multiple Regression Outputs'!$B$24+Q11*'Multiple Regression Outputs'!$B$25+R11*'Multiple Regression Outputs'!$B$26+S11*'Multiple Regression Outputs'!$B$27+T11*'Multiple Regression Outputs'!$B$28 -> 808141.23 | V11: =F11-U11 -> -29130.291 | X11: STR-1023 | Y11: 2025-02-01 | Z11: South | AA11: Mall | AB11: 627171.9 | AC11: 764038.71 | AD11: -136866.81
A12: 11 | B12: STR-1003 | C12: 2025-03-01 | D12: North | E12: Airport | F12: 723060.76 | G12: 34285.21 | H12: 9172 | I12: 0.213 | J12: 22 | K12: 88.3 | L12: 10.46 | M12: 1 | N12: 3.8 | O12: 0 | P12: 0 | Q12: 0 | R12: 1 | S12: 0 | T12: 0 | U12: ='Multiple Regression Outputs'!$B$14+G12*'Multiple Regression Outputs'!$B$15+H12*'Multiple Regression Outputs'!$B$16+I12*'Multiple Regression Outputs'!$B$17+J12*'Multiple Regression Outputs'!$B$18+K12*'Multiple Regression Outputs'!$B$19+L12*'Multiple Regression Outputs'!$B$20+M12*'Multiple Regression Outputs'!$B$21+N12*'Multiple Regression Outputs'!$B$22+O12*'Multiple Regression Outputs'!$B$23+P12*'Multiple Regression Outputs'!$B$24+Q12*'Multiple Regression Outputs'!$B$25+R12*'Multiple Regression Outputs'!$B$26+S12*'Multiple Regression Outputs'!$B$27+T12*'Multiple Regression Outputs'!$B$28 -> 754001.88 | V12: =F12-U12 -> -30941.12 | X12: STR-1017 | Y12: 2025-03-01 | Z12: West | AA12: High Street | AB12: 685379.08 | AC12: 805279.85 | AD12: -119900.77
A13: 12 | B13: STR-1003 | C13: 2025-04-01 | D13: North | E13: Airport | F13: 910791.94 | G13: 67979.88 | H13: 11230 | I13: 0.002 | J13: 28 | K13: 85.3 | L13: 7.16 | M13: 0 | N13: 3.8 | O13: 0 | P13: 0 | Q13: 0 | R13: 1 | S13: 0 | T13: 0 | U13: ='Multiple Regression Outputs'!$B$14+G13*'Multiple Regression Outputs'!$B$15+H13*'Multiple Regression Outputs'!$B$16+I13*'Multiple Regression Outputs'!$B$17+J13*'Multiple Regression Outputs'!$B$18+K13*'Multiple Regression Outputs'!$B$19+L13*'Multiple Regression Outputs'!$B$20+M13*'Multiple Regression Outputs'!$B$21+N13*'Multiple Regression Outputs'!$B$22+O13*'Multiple Regression Outputs'!$B$23+P13*'Multiple Regression Outputs'!$B$24+Q13*'Multiple Regression Outputs'!$B$25+R13*'Multiple Regression Outputs'!$B$26+S13*'Multiple Regression Outputs'!$B$27+T13*'Multiple Regression Outputs'!$B$28 -> 867782.45 | V13: =F13-U13 -> 43009.492 | X13: STR-1012 | Y13: 2025-01-01 | Z13: West | AA13: Residential | AB13: 595467.6 | AC13: 709913.78 | AD13: -114446.18
A14: 13 | B14: STR-1004 | C14: 2025-01-01 | D14: East | E14: Residential | F14: 922168.6 | G14: 71828.26 | H14: 12775 | I14: 0.116 | J14: 30 | K14: 81.7 | L14: 4.24 | M14: 1 | N14: 4.2 | O14: 0 | P14: 0 | Q14: 1 | R14: 0 | S14: 0 | T14: 0 | U14: ='Multiple Regression Outputs'!$B$14+G14*'Multiple Regression Outputs'!$B$15+H14*'Multiple Regression Outputs'!$B$16+I14*'Multiple Regression Outputs'!$B$17+J14*'Multiple Regression Outputs'!$B$18+K14*'Multiple Regression Outputs'!$B$19+L14*'Multiple Regression Outputs'!$B$20+M14*'Multiple Regression Outputs'!$B$21+N14*'Multiple Regression Outputs'!$B$22+O14*'Multiple Regression Outputs'!$B$23+P14*'Multiple Regression Outputs'!$B$24+Q14*'Multiple Regression Outputs'!$B$25+R14*'Multiple Regression Outputs'!$B$26+S14*'Multiple Regression Outputs'!$B$27+T14*'Multiple Regression Outputs'!$B$28 -> 881520.79 | V14: =F14-U14 -> 40647.806 | X14: STR-1007 | Y14: 2025-02-01 | Z14: West | AA14: Mall | AB14: 800451.94 | AC14: 912344.87 | AD14: -111892.93
A15: 14 | B15: STR-1004 | C15: 2025-02-01 | D15: East | E15: Residential | F15: 726606.28 | G15: 55716.82 | H15: 10054 | I15: 0.146 | J15: 24 | K15: 84.9 | L15: 1.06 | M15: 0 | N15: 4.3 | O15: 0 | P15: 0 | Q15: 1 | R15: 0 | S15: 0 | T15: 0 | U15: ='Multiple Regression Outputs'!$B$14+G15*'Multiple Regression Outputs'!$B$15+H15*'Multiple Regression Outputs'!$B$16+I15*'Multiple Regression Outputs'!$B$17+J15*'Multiple Regression Outputs'!$B$18+K15*'Multiple Regression Outputs'!$B$19+L15*'Multiple Regression Outputs'!$B$20+M15*'Multiple Regression Outputs'!$B$21+N15*'Multiple Regression Outputs'!$B$22+O15*'Multiple Regression Outputs'!$B$23+P15*'Multiple Regression Outputs'!$B$24+Q15*'Multiple Regression Outputs'!$B$25+R15*'Multiple Regression Outputs'!$B$26+S15*'Multiple Regression Outputs'!$B$27+T15*'Multiple Regression Outputs'!$B$28 -> 772183.54 | V15: =F15-U15 -> -45577.263 | X15: STR-1060 | Y15: 2025-01-01 | Z15: West | AA15: Mall | AB15: 721079.35 | AC15: 808021.71 | AD15: -86942.359
A16: 15 | B16: STR-1004 | C16: 2025-03-01 | D16: East | E16: Residential | F16: 746501.09 | G16: 59909.51 | H16: 8895 | I16: 0.228 | J16: 23 | K16: 88.8 | L16: 0.27 | M16: 0 | N16: 4.3 | O16: 0 | P16: 0 | Q16: 1 | R16: 0 | S16: 0 | T16: 0 | U16: ='Multiple Regression Outputs'!$B$14+G16*'Multiple Regression Outputs'!$B$15+H16*'Multiple Regression Outputs'!$B$16+I16*'Multiple Regression Outputs'!$B$17+J16*'Multiple Regression Outputs'!$B$18+K16*'Multiple Regression Outputs'!$B$19+L16*'Multiple Regression Outputs'!$B$20+M16*'Multiple Regression Outputs'!$B$21+N16*'Multiple Regression Outputs'!$B$22+O16*'Multiple Regression Outputs'!$B$23+P16*'Multiple Regression Outputs'!$B$24+Q16*'Multiple Regression Outputs'!$B$25+R16*'Multiple Regression Outputs'!$B$26+S16*'Multiple Regression Outputs'!$B$27+T16*'Multiple Regression Outputs'!$B$28 -> 753342.14 | V16: =F16-U16 -> -6841.0467
A17: 16 | B17: STR-1004 | C17: 2025-04-01 | D17: East | E17: Residential | F17: 834017.02 | G17: 75305.71 | H17: 10940 | I17: 0.006 | J17: 26 | K17: 76.5 | L17: 1.32 | M17: 0 | N17: 4.5 | O17: 0 | P17: 0 | Q17: 1 | R17: 0 | S17: 0 | T17: 0 | U17: ='Multiple Regression Outputs'!$B$14+G17*'Multiple Regression Outputs'!$B$15+H17*'Multiple Regression Outputs'!$B$16+I17*'Multiple Regression Outputs'!$B$17+J17*'Multiple Regression Outputs'!$B$18+K17*'Multiple Regression Outputs'!$B$19+L17*'Multiple Regression Outputs'!$B$20+M17*'Multiple Regression Outputs'!$B$21+N17*'Multiple Regression Outputs'!$B$22+O17*'Multiple Regression Outputs'!$B$23+P17*'Multiple Regression Outputs'!$B$24+Q17*'Multiple Regression Outputs'!$B$25+R17*'Multiple Regression Outputs'!$B$26+S17*'Multiple Regression Outputs'!$B$27+T17*'Multiple Regression Outputs'!$B$28 -> 808780.83 | V17: =F17-U17 -> 25236.195
A18: 17 | B18: STR-1005 | C18: 2025-01-01 | D18: South | E18: Residential | F18: 666152.52 | G18: 48804.22 | H18: 7057 | I18: 0.005 | J18: 15 | K18: 87.7 | L18: 1.22 | M18: 0 | N18: 3.7 | O18: 0 | P18: 0 | Q18: 1 | R18: 0 | S18: 1 | T18: 0 | U18: ='Multiple Regression Outputs'!$B$14+G18*'Multiple Regression Outputs'!$B$15+H18*'Multiple Regression Outputs'!$B$16+I18*'Multiple Regression Outputs'!$B$17+J18*'Multiple Regression Outputs'!$B$18+K18*'Multiple Regression Outputs'!$B$19+L18*'Multiple Regression Outputs'!$B$20+M18*'Multiple Regression Outputs'!$B$21+N18*'Multiple Regression Outputs'!$B$22+O18*'Multiple Regression Outputs'!$B$23+P18*'Multiple Regression Outputs'!$B$24+Q18*'Multiple Regression Outputs'!$B$25+R18*'Multiple Regression Outputs'!$B$26+S18*'Multiple Regression Outputs'!$B$27+T18*'Multiple Regression Outputs'!$B$28 -> 677740.89 | V18: =F18-U18 -> -11588.368
A19: 18 | B19: STR-1005 | C19: 2025-02-01 | D19: South | E19: Residential | F19: 573155.19 | G19: 59117.9 | H19: 4263 | I19: 0.119 | J19: 9 | K19: 87.6 | L19: 4.01 | M19: 0 | N19: 3.6 | O19: 0 | P19: 0 | Q19: 1 | R19: 0 | S19: 1 | T19: 0 | U19: ='Multiple Regression Outputs'!$B$14+G19*'Multiple Regression Outputs'!$B$15+H19*'Multiple Regression Outputs'!$B$16+I19*'Multiple Regression Outputs'!$B$17+J19*'Multiple Regression Outputs'!$B$18+K19*'Multiple Regression Outputs'!$B$19+L19*'Multiple Regression Outputs'!$B$20+M19*'Multiple Regression Outputs'!$B$21+N19*'Multiple Regression Outputs'!$B$22+O19*'Multiple Regression Outputs'!$B$23+P19*'Multiple Regression Outputs'!$B$24+Q19*'Multiple Regression Outputs'!$B$25+R19*'Multiple Regression Outputs'!$B$26+S19*'Multiple Regression Outputs'!$B$27+T19*'Multiple Regression Outputs'!$B$28 -> 576940.77 | V19: =F19-U19 -> -3785.5826
A20: 19 | B20: STR-1005 | C20: 2025-03-01 | D20: South | E20: Residential | F20: 666573.2 | G20: 78831.12 | H20: 5538 | I20: 0 | J20: 15 | K20: 94.1 | L20: 0.2 | M20: 0 | N20: 3.9 | O20: 0 | P20: 0 | Q20: 1 | R20: 0 | S20: 1 | T20: 0 | U20: ='Multiple Regression Outputs'!$B$14+G20*'Multiple Regression Outputs'!$B$15+H20*'Multiple Regression Outputs'!$B$16+I20*'Multiple Regression Outputs'!$B$17+J20*'Multiple Regression Outputs'!$B$18+K20*'Multiple Regression Outputs'!$B$19+L20*'Multiple Regression Outputs'!$B$20+M20*'Multiple Regression Outputs'!$B$21+N20*'Multiple Regression Outputs'!$B$22+O20*'Multiple Regression Outputs'!$B$23+P20*'Multiple Regression Outputs'!$B$24+Q20*'Multiple Regression Outputs'!$B$25+R20*'Multiple Regression Outputs'!$B$26+S20*'Multiple Regression Outputs'!$B$27+T20*'Multiple Regression Outputs'!$B$28 -> 698360.73 | V20: =F20-U20 -> -31787.534
A21: 20 | B21: STR-1005 | C21: 2025-04-01 | D21: South | E21: Residential | F21: 591619.95 | G21: 41441.93 | H21: 4865 | I21: 0.158 | J21: 16 | K21: 88.3 | L21: 0.5 | M21: 0 | N21: 4 | O21: 0 | P21: 0 | Q21: 1 | R21: 0 | S21: 1 | T21: 0 | U21: ='Multiple Regression Outputs'!$B$14+G21*'Multiple Regression Outputs'!$B$15+H21*'Multiple Regression Outputs'!$B$16+I21*'Multiple Regression Outputs'!$B$17+J21*'Multiple Regression Outputs'!$B$18+K21*'Multiple Regression Outputs'!$B$19+L21*'Multiple Regression Outputs'!$B$20+M21*'Multiple Regression Outputs'!$B$21+N21*'Multiple Regression Outputs'!$B$22+O21*'Multiple Regression Outputs'!$B$23+P21*'Multiple Regression Outputs'!$B$24+Q21*'Multiple Regression Outputs'!$B$25+R21*'Multiple Regression Outputs'!$B$26+S21*'Multiple Regression Outputs'!$B$27+T21*'Multiple Regression Outputs'!$B$28 -> 614175.9 | V21: =F21-U21 -> -22555.954
A22: 21 | B22: STR-1006 | C22: 2025-01-01 | D22: North | E22: Residential | F22: 415721.82 | G22: 30356.28 | H22: 2822 | I22: 0.231 | J22: 9 | K22: 84.8 | L22: 6.95 | M22: 0 | N22: 5 | O22: 0 | P22: 0 | Q22: 1 | R22: 1 | S22: 0 | T22: 0 | U22: ='Multiple Regression Outputs'!$B$14+G22*'Multiple Regression Outputs'!$B$15+H22*'Multiple Regression Outputs'!$B$16+I22*'Multiple Regression Outputs'!$B$17+J22*'Multiple Regression Outputs'!$B$18+K22*'Multiple Regression Outputs'!$B$19+L22*'Multiple Regression Outputs'!$B$20+M22*'Multiple Regression Outputs'!$B$21+N22*'Multiple Regression Outputs'!$B$22+O22*'Multiple Regression Outputs'!$B$23+P22*'Multiple Regression Outputs'!$B$24+Q22*'Multiple Regression Outputs'!$B$25+R22*'Multiple Regression Outputs'!$B$26+S22*'Multiple Regression Outputs'!$B$27+T22*'Multiple Regression Outputs'!$B$28 -> 485820.75 | V22: =F22-U22 -> -70098.927
A23: 22 | B23: STR-1006 | C23: 2025-02-01 | D23: North | E23: Residential | F23: 491905.13 | G23: 33518.88 | H23: 2121 | I23: 0.176 | J23: 8 | K23: 88.5 | L23: 0.2 | M23: 0 | N23: 5 | O23: 0 | P23: 0 | Q23: 1 | R23: 1 | S23: 0 | T23: 0 | U23: ='Multiple Regression Outputs'!$B$14+G23*'Multiple Regression Outputs'!$B$15+H23*'Multiple Regression Outputs'!$B$16+I23*'Multiple Regression Outputs'!$B$17+J23*'Multiple Regression Outputs'!$B$18+K23*'Multiple Regression Outputs'!$B$19+L23*'Multiple Regression Outputs'!$B$20+M23*'Multiple Regression Outputs'!$B$21+N23*'Multiple Regression Outputs'!$B$22+O23*'Multiple Regression Outputs'!$B$23+P23*'Multiple Regression Outputs'!$B$24+Q23*'Multiple Regression Outputs'!$B$25+R23*'Multiple Regression Outputs'!$B$26+S23*'Multiple Regression Outputs'!$B$27+T23*'Multiple Regression Outputs'!$B$28 -> 503781.98 | V23: =F23-U23 -> -11876.845
A24: 23 | B24: STR-1006 | C24: 2025-03-01 | D24: North | E24: Residential | F24: 555929.4 | G24: 42267.37 | H24: 3364 | I24: 0.16 | J24: 13 | K24: 82 | L24: 1.61 | M24: 1 | N24: 4.6 | O24: 0 | P24: 0 | Q24: 1 | R24: 1 | S24: 0 | T24: 0 | U24: ='Multiple Regression Outputs'!$B$14+G24*'Multiple Regression Outputs'!$B$15+H24*'Multiple Regression Outputs'!$B$16+I24*'Multiple Regression Outputs'!$B$17+J24*'Multiple Regression Outputs'!$B$18+K24*'Multiple Regression Outputs'!$B$19+L24*'Multiple Regression Outputs'!$B$20+M24*'Multiple Regression Outputs'!$B$21+N24*'Multiple Regression Outputs'!$B$22+O24*'Multiple Regression Outputs'!$B$23+P24*'Multiple Regression Outputs'!$B$24+Q24*'Multiple Regression Outputs'!$B$25+R24*'Multiple Regression Outputs'!$B$26+S24*'Multiple Regression Outputs'!$B$27+T24*'Multiple Regression Outputs'!$B$28 -> 551949.2 | V24: =F24-U24 -> 3980.1975
A25: 24 | B25: STR-1006 | C25: 2025-04-01 | D25: North | E25: Residential | F25: 565810.99 | G25: 62060.43 | H25: 2613 | I25: 0.216 | J25: 12 | K25: 92.1 | L25: 1.55 | M25: 0 | N25: 4.7 | O25: 0 | P25: 0 | Q25: 1 | R25: 1 | S25: 0 | T25: 0 | U25: ='Multiple Regression Outputs'!$B$14+G25*'Multiple Regression Outputs'!$B$15+H25*'Multiple Regression Outputs'!$B$16+I25*'Multiple Regression Outputs'!$B$17+J25*'Multiple Regression Outputs'!$B$18+K25*'Multiple Regression Outputs'!$B$19+L25*'Multiple Regression Outputs'!$B$20+M25*'Multiple Regression Outputs'!$B$21+N25*'Multiple Regression Outputs'!$B$22+O25*'Multiple Regression Outputs'!$B$23+P25*'Multiple Regression Outputs'!$B$24+Q25*'Multiple Regression Outputs'!$B$25+R25*'Multiple Regression Outputs'!$B$26+S25*'Multiple Regression Outputs'!$B$27+T25*'Multiple Regression Outputs'!$B$28 -> 566778.16 | V25: =F25-U25 -> -967.17114
A26: 25 | B26: STR-1007 | C26: 2025-01-01 | D26: West | E26: Mall | F26: 811771.14 | G26: 57696.69 | H26: 10218 | I26: 0.121 | J26: 25 | K26: 94.8 | L26: 2.99 | M26: 0 | N26: 3.5 | O26: 0 | P26: 1 | Q26: 0 | R26: 0 | S26: 0 | T26: 1 | U26: ='Multiple Regression Outputs'!$B$14+G26*'Multiple Regression Outputs'!$B$15+H26*'Multiple Regression Outputs'!$B$16+I26*'Multiple Regression Outputs'!$B$17+J26*'Multiple Regression Outputs'!$B$18+K26*'Multiple Regression Outputs'!$B$19+L26*'Multiple Regression Outputs'!$B$20+M26*'Multiple Regression Outputs'!$B$21+N26*'Multiple Regression Outputs'!$B$22+O26*'Multiple Regression Outputs'!$B$23+P26*'Multiple Regression Outputs'!$B$24+Q26*'Multiple Regression Outputs'!$B$25+R26*'Multiple Regression Outputs'!$B$26+S26*'Multiple Regression Outputs'!$B$27+T26*'Multiple Regression Outputs'!$B$28 -> 855398.7 | V26: =F26-U26 -> -43627.555
A27: 26 | B27: STR-1007 | C27: 2025-02-01 | D27: West | E27: Mall | F27: 800451.94 | G27: 172415.52 | H27: 8927 | I27: 0.14 | J27: 22 | K27: 86.2 | L27: 7.04 | M27: 0 | N27: 3.9 | O27: 0 | P27: 1 | Q27: 0 | R27: 0 | S27: 0 | T27: 1 | U27: ='Multiple Regression Outputs'!$B$14+G27*'Multiple Regression Outputs'!$B$15+H27*'Multiple Regression Outputs'!$B$16+I27*'Multiple Regression Outputs'!$B$17+J27*'Multiple Regression Outputs'!$B$18+K27*'Multiple Regression Outputs'!$B$19+L27*'Multiple Regression Outputs'!$B$20+M27*'Multiple Regression Outputs'!$B$21+N27*'Multiple Regression Outputs'!$B$22+O27*'Multiple Regression Outputs'!$B$23+P27*'Multiple Regression Outputs'!$B$24+Q27*'Multiple Regression Outputs'!$B$25+R27*'Multiple Regression Outputs'!$B$26+S27*'Multiple Regression Outputs'!$B$27+T27*'Multiple Regression Outputs'!$B$28 -> 912344.87 | V27: =F27-U27 -> -111892.93
... A321: 320 | B321: STR-1080 | C321: 2025-04-01 | D321: East | E321: Residential | F321: 559660.84 | G321: 40553.11 | H321: 5317 | I321: 0.165 | J321: 17 | K321: 84.3 | L321: 11.82 | M321: 0 | N321: 4.1 | O321: 0 | P321: 0 | Q321: 1 | R321: 0 | S321: 0 | T321: 0 | U321: ='Multiple Regression Outputs'!$B$14+G321*'Multiple Regression Outputs'!$B$15+H321*'Multiple Regression Outputs'!$B$16+I321*'Multiple Regression Outputs'!$B$17+J321*'Multiple Regression Outputs'!$B$18+K321*'Multiple Regression Outputs'!$B$19+L321*'Multiple Regression Outputs'!$B$20+M321*'Multiple Regression Outputs'!$B$21+N321*'Multiple Regression Outputs'!$B$22+O321*'Multiple Regression Outputs'!$B$23+P321*'Multiple Regression Outputs'!$B$24+Q321*'Multiple Regression Outputs'!$B$25+R321*'Multiple Regression Outputs'!$B$26+S321*'Multiple Regression Outputs'!$B$27+T321*'Multiple Regression Outputs'!$B$28 -> 557669.31 | V321: =F321-U321 -> 1991.5298

Sheet Model Comparison
A1: Model Comparison Summary
A3: Model name | B3: Variables used | C3: R-squared | D3: Significant variables | E3: Business usefulness | F3: Limitations
A4: Simple: marketing_spend | B4: DV: monthly_sales; IV: marketing_spend | C4: 0.16724469 | D4: marketing_spend | E4: Useful for directional insight; limited because it excludes other business drivers. | F4: Single-variable model; may suffer omitted-variable bias.
A5: Simple: footfall | B5: DV: monthly_sales; IV: footfall | C5: 0.73628534 | D5: footfall | E5: Useful for directional insight; limited because it excludes other business drivers. | F5: Single-variable model; may suffer omitted-variable bias.
A6: Simple: avg_discount_pct | B6: DV: monthly_sales; IV: avg_discount_pct | C6: 0.008290503 | D6: None at 5% | E6: Useful for directional insight; limited because it excludes other business drivers. | F6: Single-variable model; may suffer omitted-variable bias.
A7: Simple: inventory_availability_pct | B7: DV: monthly_sales; IV: inventory_availability_pct | C7: 0.013115016 | D7: inventory_availability_pct | E7: Useful for directional insight; limited because it excludes other business drivers. | F7: Single-variable model; may suffer omitted-variable bias.
A8: Simple: customer_rating | B8: DV: monthly_sales; IV: customer_rating | C8: 0.00069845266 | D8: None at 5% | E8: Useful for directional insight; limited because it excludes other business drivers. | F8: Single-variable model; may suffer omitted-variable bias.
A9: Simple: staff_count | B9: DV: monthly_sales; IV: staff_count | C9: 0.65229045 | D9: staff_count | E9: Useful for directional insight; limited because it excludes other business drivers. | F9: Single-variable model; may suffer omitted-variable bias.
A10: Simple: competitor_distance_km | B10: DV: monthly_sales; IV: competitor_distance_km | C10: 0.011443607 | D10: Borderline: competitor_distance_km | E10: Useful for directional insight; limited because it excludes other business drivers. | F10: Single-variable model; may suffer omitted-variable bias.
A11: Simple: holiday_flag | B11: DV: monthly_sales; IV: holiday_flag | C11: 0.038128574 | D11: holiday_flag | E11: Useful for directional insight; limited because it excludes other business drivers. | F11: Single-variable model; may suffer omitted-variable bias.
A12: Multiple: final selected model | B12: DV: monthly_sales; IVs: marketing_spend, footfall, avg_discount_pct, staff_count, inventory_availability_pct, competitor_distance_km, holiday_flag, customer_rating, store_type dummies, region dummies | C12: 0.85698739 | D12: marketing_spend, footfall, staff_count, inventory_availability_pct, competitor_distance_km, holiday_flag, customer_rating, store_type_High_Street, store_type_Residential, region_South, region_West | E12: Best decision model because it explains the most variation and controls for store type and region. | F12: Association only; may exclude local events, price mix, promotions, seasonality depth, and store-level fixed effects.
